jsonex/__init__.py
jsonex/custom_data.py
tests/__init__.py
jsonex-1.3.dist-info/LICENSE
jsonex-1.3.dist-info/METADATA
jsonex-1.3.dist-info/WHEEL
jsonex-1.3.dist-info/top_level.txt
jsonex-1.3.dist-info/RECORD
