Metadata-Version: 2.1
Name: jsonex
Version: 1.3
Summary: Json library
Author: Krzysztof Żyłka
Classifier: Programming Language :: Python :: 3
Classifier: License :: OSI Approved :: MIT License
Classifier: Operating System :: OS Independent
License-File: LICENSE
